pypmml/__init__.py
pypmml/base.py
pypmml/elements.py
pypmml/jvm.py
pypmml/metadata.py
pypmml/model.py
pypmml/utils.py
pypmml/version.py
pypmml/jars/__init__.py
pypmml/jars/commons-lang3-3.15.0.jar
pypmml/jars/commons-math3-3.6.1.jar
pypmml/jars/commons-text-1.12.0.jar
pypmml/jars/pmml4s_2.13-1.5.7.jar
pypmml/jars/scala-library-2.13.14.jar
pypmml/jars/scala-reflect-2.13.14.jar
pypmml/jars/spray-json_2.13-1.3.6.jar
pypmml-1.5.7.dist-info/licenses/LICENSE
pypmml-1.5.7.dist-info/METADATA
pypmml-1.5.7.dist-info/WHEEL
pypmml-1.5.7.dist-info/top_level.txt
pypmml-1.5.7.dist-info/RECORD
